{
  "metainfo" : {
    "type" : "Databricks",
    "fabricId" : "244",
    "jobId" : "jobs/as",
    "name" : "as",
    "schedule" : "None",
    "scheduleTimeZone" : "UTC",
    "jobClusterMode" : {
      "clusterMode" : "Single"
    },
    "enabled" : false,
    "defaultClusterSize" : "small-update",
    "alerting" : {
      "emails" : "",
      "onStart" : false,
      "onSuccess" : false,
      "onFailure" : false
    },
    "maxConcurrentRuns" : 1,
    "processDefaultSettings" : {
      "type" : "Inherited",
      "retries" : 0,
      "alerting" : {
        "emails" : "",
        "onStart" : false,
        "onSuccess" : false,
        "onFailure" : false
      }
    },
    "availableFabrics" : [ {
      "id" : "1161",
      "name" : "test-list-fab",
      "clusterSizes" : {
        "default" : "small",
        "availableClusterSizes" : [ "small" ]
      },
      "pylibsResolutionMode" : {
        "PublicCentral" : { }
      },
      "scalalibsResolutionMode" : {
        "PublicCentral" : { }
      }
    }, {
      "id" : "918",
      "name" : "databricks",
      "clusterSizes" : {
        "default" : "small",
        "availableClusterSizes" : [ "small" ]
      },
      "pylibsResolutionMode" : {
        "PublicCentral" : { }
      },
      "scalalibsResolutionMode" : {
        "PublicCentral" : { }
      }
    }, {
      "id" : "1221",
      "name" : "fb3",
      "clusterSizes" : {
        "default" : "small",
        "availableClusterSizes" : [ "small" ]
      },
      "pylibsResolutionMode" : {
        "PublicCentral" : { }
      },
      "scalalibsResolutionMode" : {
        "PublicCentral" : { }
      }
    }, {
      "id" : "1183",
      "name" : "test-list-fab-1",
      "clusterSizes" : {
        "default" : "small",
        "availableClusterSizes" : [ "small" ]
      },
      "pylibsResolutionMode" : {
        "PublicCentral" : { }
      },
      "scalalibsResolutionMode" : {
        "PublicCentral" : { }
      }
    }, {
      "id" : "244",
      "name" : "dev_own",
      "clusterSizes" : {
        "default" : "small-update",
        "availableClusterSizes" : [ "small-update", "small_14", "small_12" ]
      },
      "pylibsResolutionMode" : {
        "PublicCentral" : { }
      },
      "scalalibsResolutionMode" : {
        "PublicCentral" : { }
      }
    }, {
      "id" : "2345",
      "name" : "fabric_00123",
      "clusterSizes" : {
        "default" : "small",
        "availableClusterSizes" : [ "small" ]
      },
      "pylibsResolutionMode" : {
        "PublicCentral" : { }
      },
      "scalalibsResolutionMode" : {
        "PublicCentral" : { }
      }
    }, {
      "id" : "1153",
      "name" : "sadfasf",
      "clusterSizes" : {
        "default" : "small",
        "availableClusterSizes" : [ "small" ]
      },
      "pylibsResolutionMode" : {
        "PublicCentral" : { }
      },
      "scalalibsResolutionMode" : {
        "PublicCentral" : { }
      }
    }, {
      "id" : "2364",
      "name" : "new_fabric_test",
      "clusterSizes" : {
        "default" : "small",
        "availableClusterSizes" : [ "small" ]
      },
      "pylibsResolutionMode" : {
        "PublicCentral" : { }
      },
      "scalalibsResolutionMode" : {
        "PublicCentral" : { }
      }
    }, {
      "id" : "2283",
      "name" : "fsfgsfg",
      "clusterSizes" : {
        "default" : "small",
        "availableClusterSizes" : [ "small" ]
      },
      "pylibsResolutionMode" : {
        "PublicCentral" : { }
      },
      "scalalibsResolutionMode" : {
        "PublicCentral" : { }
      }
    }, {
      "id" : "2268",
      "name" : "Entra1",
      "clusterSizes" : {
        "default" : "small",
        "availableClusterSizes" : [ "small", "multi" ]
      },
      "pylibsResolutionMode" : {
        "PublicCentral" : { }
      },
      "scalalibsResolutionMode" : {
        "PublicCentral" : { }
      }
    }, {
      "id" : "2272",
      "name" : "check186987",
      "clusterSizes" : {
        "default" : "small",
        "availableClusterSizes" : [ "small" ]
      },
      "pylibsResolutionMode" : {
        "CustomArtifactory" : {
          "url" : "https://pypi.python.org/simple"
        }
      },
      "scalalibsResolutionMode" : {
        "CustomArtifactory" : {
          "url" : "https://repo1.maven.org/"
        }
      }
    }, {
      "id" : "2344",
      "name" : "fabric_001",
      "clusterSizes" : {
        "default" : "small",
        "availableClusterSizes" : [ "small" ]
      },
      "pylibsResolutionMode" : {
        "PublicCentral" : { }
      },
      "scalalibsResolutionMode" : {
        "PublicCentral" : { }
      }
    }, {
      "id" : "1408",
      "name" : "dev1",
      "clusterSizes" : {
        "default" : "small",
        "availableClusterSizes" : [ "small" ]
      },
      "pylibsResolutionMode" : {
        "PublicCentral" : { }
      },
      "scalalibsResolutionMode" : {
        "PublicCentral" : { }
      }
    }, {
      "id" : "571",
      "name" : "ebs_test",
      "clusterSizes" : {
        "default" : "small",
        "availableClusterSizes" : [ "small" ]
      },
      "pylibsResolutionMode" : {
        "PublicCentral" : { }
      },
      "scalalibsResolutionMode" : {
        "PublicCentral" : { }
      }
    }, {
      "id" : "2103",
      "name" : "test-entra-fabric",
      "clusterSizes" : {
        "default" : "small",
        "availableClusterSizes" : [ "small" ]
      },
      "pylibsResolutionMode" : {
        "PublicCentral" : { }
      },
      "scalalibsResolutionMode" : {
        "PublicCentral" : { }
      }
    }, {
      "id" : "2199",
      "name" : "fab1",
      "clusterSizes" : {
        "default" : "small",
        "availableClusterSizes" : [ "small" ]
      },
      "pylibsResolutionMode" : {
        "PublicCentral" : { }
      },
      "scalalibsResolutionMode" : {
        "PublicCentral" : { }
      }
    }, {
      "id" : "2361",
      "name" : "pm_fabric_db",
      "clusterSizes" : {
        "default" : "small",
        "availableClusterSizes" : [ "small" ]
      },
      "pylibsResolutionMode" : {
        "PublicCentral" : { }
      },
      "scalalibsResolutionMode" : {
        "PublicCentral" : { }
      }
    }, {
      "id" : "2297",
      "name" : "test_pm_secrets101",
      "clusterSizes" : {
        "default" : "small",
        "availableClusterSizes" : [ "small" ]
      },
      "pylibsResolutionMode" : {
        "PublicCentral" : { }
      },
      "scalalibsResolutionMode" : {
        "PublicCentral" : { }
      }
    }, {
      "id" : "2112",
      "name" : "asdfdsf",
      "clusterSizes" : {
        "default" : "small",
        "availableClusterSizes" : [ "small" ]
      },
      "pylibsResolutionMode" : {
        "PublicCentral" : { }
      },
      "scalalibsResolutionMode" : {
        "PublicCentral" : { }
      }
    }, {
      "id" : "2362",
      "name" : "test_PM_fabric",
      "clusterSizes" : {
        "default" : "small",
        "availableClusterSizes" : [ "small" ]
      },
      "pylibsResolutionMode" : {
        "PublicCentral" : { }
      },
      "scalalibsResolutionMode" : {
        "PublicCentral" : { }
      }
    }, {
      "id" : "2125",
      "name" : "sadsadsadasd",
      "clusterSizes" : {
        "default" : "small",
        "availableClusterSizes" : [ "small", "dfgh", "assassa" ]
      },
      "pylibsResolutionMode" : {
        "PublicCentral" : { }
      },
      "scalalibsResolutionMode" : {
        "PublicCentral" : { }
      }
    }, {
      "id" : "2270",
      "name" : "EntraCheck",
      "clusterSizes" : {
        "default" : "small",
        "availableClusterSizes" : [ "small", "multicheck" ]
      },
      "pylibsResolutionMode" : {
        "PublicCentral" : { }
      },
      "scalalibsResolutionMode" : {
        "PublicCentral" : { }
      }
    }, {
      "id" : "243",
      "name" : "dev",
      "clusterSizes" : {
        "default" : "Small",
        "availableClusterSizes" : [ "Small" ]
      },
      "pylibsResolutionMode" : {
        "PublicCentral" : { }
      },
      "scalalibsResolutionMode" : {
        "PublicCentral" : { }
      }
    }, {
      "id" : "2333",
      "name" : "Databricks_non_admin_fabric",
      "clusterSizes" : {
        "default" : "small",
        "availableClusterSizes" : [ "small" ]
      },
      "pylibsResolutionMode" : {
        "PublicCentral" : { }
      },
      "scalalibsResolutionMode" : {
        "PublicCentral" : { }
      }
    }, {
      "id" : "1184",
      "name" : "test-list-fab-2",
      "clusterSizes" : {
        "default" : "small",
        "availableClusterSizes" : [ "small" ]
      },
      "pylibsResolutionMode" : {
        "PublicCentral" : { }
      },
      "scalalibsResolutionMode" : {
        "PublicCentral" : { }
      }
    }, {
      "id" : "2366",
      "name" : "TestAvcsDatabricks",
      "clusterSizes" : {
        "default" : "small",
        "availableClusterSizes" : [ "small" ]
      },
      "pylibsResolutionMode" : {
        "PublicCentral" : { }
      },
      "scalalibsResolutionMode" : {
        "PublicCentral" : { }
      }
    }, {
      "id" : "1869",
      "name" : "ddddd",
      "clusterSizes" : {
        "default" : "small",
        "availableClusterSizes" : [ "small", "jk", "xz", "cv", "q" ]
      },
      "pylibsResolutionMode" : {
        "PublicCentral" : { }
      },
      "scalalibsResolutionMode" : {
        "PublicCentral" : { }
      }
    }, {
      "id" : "370",
      "name" : "databricks_fabric_13_3_LTS",
      "clusterSizes" : {
        "default" : "3.4.1_spark_small_job",
        "availableClusterSizes" : [ "3.4.1_spark_small_job", "12_2_LTS_JOB", "hashi_vault" ]
      },
      "pylibsResolutionMode" : {
        "PublicCentral" : { }
      },
      "scalalibsResolutionMode" : {
        "PublicCentral" : { }
      }
    } ]
  },
  "processes" : { },
  "connections" : [ ]
}